liasdfiosql/__init__.py
liasdfiosql/__main__.py
liasdfiosql/cli.py
liasdfiosql/core.py
liasdfiosql-0.4.2.dist-info/licenses/LICENSE
liasdfiosql-0.4.2.dist-info/METADATA
liasdfiosql-0.4.2.dist-info/WHEEL
liasdfiosql-0.4.2.dist-info/entry_points.txt
liasdfiosql-0.4.2.dist-info/top_level.txt
liasdfiosql-0.4.2.dist-info/RECORD
