Metadata-Version: 2.4
Name: liasdfiosql
Version: 0.4.2
Summary: Sandboxed file CLI with fixed webhook curl and safe helpers (ls/cat/find/grep/sleep).
Author: liasdfio
License: MIT License
Keywords: cli,sandbox,webhook,filesystem
Classifier: Programming Language :: Python :: 3
Classifier: License :: OSI Approved :: MIT License
Classifier: Operating System :: OS Independent
Classifier: Environment :: Console
Classifier: Topic :: Utilities
Requires-Python: >=3.9
License-File: LICENSE
Provides-Extra: test
Requires-Dist: pytest; extra == "test"
Dynamic: license-file
